third_party_license_file_generator/__init__.py
third_party_license_file_generator/__main__.py
third_party_license_file_generator/site_packages.py
third_party_license_file_generator/licenses/__init__.py
third_party_license_file_generator/licenses/apache_1_1.py
third_party_license_file_generator/licenses/apache_2_0.py
third_party_license_file_generator/licenses/bsd_2_clause.py
third_party_license_file_generator/licenses/bsd_3_clause.py
third_party_license_file_generator/licenses/gpl_2_0.py
third_party_license_file_generator/licenses/gpl_3_0.py
third_party_license_file_generator/licenses/isc.py
third_party_license_file_generator/licenses/lgpl_2_1.py
third_party_license_file_generator/licenses/lgpl_3_0.py
third_party_license_file_generator/licenses/mit.py
third_party_license_file_generator/licenses/mpl_1_0.py
third_party_license_file_generator/licenses/mpl_1_1.py
third_party_license_file_generator/licenses/mpl_2_0.py
third_party_license_file_generator/licenses/pil.py
third_party_license_file_generator/licenses/python_2_0.py
third_party_license_file_generator-2023.2.22.data/data/README.md
third_party_license_file_generator-2023.2.22.dist-info/LICENSE
third_party_license_file_generator-2023.2.22.dist-info/METADATA
third_party_license_file_generator-2023.2.22.dist-info/WHEEL
third_party_license_file_generator-2023.2.22.dist-info/top_level.txt
third_party_license_file_generator-2023.2.22.dist-info/RECORD
