Metadata-Version: 2.1
Name: third-party-license-file-generator
Version: 2023.2.22
Summary: The Python third_party_license_file_generator is aimed at distilling down the appropriate license for one or many pip "requirements" files into a single file; it supports Python2.7 and Python3.
Home-page: https://github.com/ftpsolutions/python-third-party-license-file-generator
Author: Edward Beech
Author-email: edward.beech@ftpsolutions.com.au
License: MIT
Keywords: sample setuptools development
Classifier: Development Status :: 3 - Alpha
Classifier: Intended Audience :: Developers
Classifier: Topic :: Software Development :: Libraries
Classifier: License :: OSI Approved :: MIT License
Classifier: Programming Language :: Python :: 2.7
Classifier: Programming Language :: Python :: 3.6
License-File: LICENSE
Requires-Dist: requests (>=2.25)
Requires-Dist: PyYAML (>=5.4)
Provides-Extra: dev
Requires-Dist: check-manifest ; extra == 'dev'
Provides-Extra: test
Requires-Dist: coverage ; extra == 'test'
